metrosaopaulo/__init__.py
metrosaopaulo/metrosaopaulo.py
metrosaopaulo-0.0.2.dist-info/LICENSE
metrosaopaulo-0.0.2.dist-info/METADATA
metrosaopaulo-0.0.2.dist-info/WHEEL
metrosaopaulo-0.0.2.dist-info/top_level.txt
metrosaopaulo-0.0.2.dist-info/RECORD
