Metadata-Version: 2.1
Name: metrosaopaulo
Version: 0.0.2
Summary: Get São Paulo Metro Status descriptions from Official Site
Home-page: https://github.com/jblancoperez/metrosaopaulo
Author: Julio Manuel Blanco Perez
Author-email: jblancoperez@gmail.com
License: UNKNOWN
Platform: UNKNOWN
Classifier: Programming Language :: Python :: 3
Classifier: License :: OSI Approved :: MIT License
Classifier: Operating System :: OS Independent
Requires-Dist: requests (==2.21.0)
